brs_kb/__init__.py
brs_kb/api_server.py
brs_kb/cli.py
brs_kb/exceptions.py
brs_kb/logger.py
brs_kb/metrics.py
brs_kb/metrics_server.py
brs_kb/payload_index.py
brs_kb/payload_testing.py
brs_kb/payloads_compat.py
brs_kb/py.typed
brs_kb/reverse_map.py
brs_kb/schema.json
brs_kb/validation.py
brs_kb/version.py
brs_kb/cli/__init__.py
brs_kb/cli/__main__.py
brs_kb/cli/cli.py
brs_kb/cli/parser.py
brs_kb/cli/commands/__init__.py
brs_kb/cli/commands/analyze_payload.py
brs_kb/cli/commands/base.py
brs_kb/cli/commands/export.py
brs_kb/cli/commands/generate_report.py
brs_kb/cli/commands/get_context.py
brs_kb/cli/commands/info.py
brs_kb/cli/commands/list_contexts.py
brs_kb/cli/commands/search_payloads.py
brs_kb/cli/commands/serve.py
brs_kb/cli/commands/test_payload.py
brs_kb/cli/commands/validate.py
brs_kb/contexts/STRUCTURE.md
brs_kb/contexts/__init__.py
brs_kb/contexts/base.py
brs_kb/contexts/default.py
brs_kb/contexts/ai/brs_kb_ctx_llm_injection.py
brs_kb/contexts/api/__init__.py
brs_kb/contexts/api/brs_kb_ctx_fetch.py
brs_kb/contexts/api/brs_kb_ctx_graphql.py
brs_kb/contexts/api/brs_kb_ctx_graphql_batch.py
brs_kb/contexts/api/brs_kb_ctx_graphql_data.py
brs_kb/contexts/api/brs_kb_ctx_graphql_mutation.py
brs_kb/contexts/api/brs_kb_ctx_graphql_persisted.py
brs_kb/contexts/api/brs_kb_ctx_graphql_query.py
brs_kb/contexts/api/brs_kb_ctx_graphql_variable.py
brs_kb/contexts/api/brs_kb_ctx_graphql_vectors.py
brs_kb/contexts/api/brs_kb_ctx_postmessage.py
brs_kb/contexts/api/brs_kb_ctx_sse.py
brs_kb/contexts/api/brs_kb_ctx_sse_data.py
brs_kb/contexts/api/brs_kb_ctx_sse_event.py
brs_kb/contexts/api/brs_kb_ctx_sse_handler.py
brs_kb/contexts/api/brs_kb_ctx_sse_id.py
brs_kb/contexts/api/brs_kb_ctx_sse_url.py
brs_kb/contexts/api/brs_kb_ctx_websocket.py
brs_kb/contexts/api/brs_kb_ctx_websocket_data.py
brs_kb/contexts/api/brs_kb_ctx_websocket_handler.py
brs_kb/contexts/api/brs_kb_ctx_websocket_message.py
brs_kb/contexts/api/brs_kb_ctx_websocket_url.py
brs_kb-4.0.2.dist-info/METADATA
brs_kb-4.0.2.dist-info/WHEEL
brs_kb-4.0.2.dist-info/entry_points.txt
brs_kb-4.0.2.dist-info/licenses/LICENSE
brs_kb-4.0.2.dist-info/RECORD
