Metadata-Version: 2.4
Name: brs-kb
Version: 4.0.2
Summary: XSS Knowledge Base — 4900+ Payloads, 169 Contexts, WAF Bypasses, Zero Dependencies
Project-URL: Homepage, https://github.com/EPTLLC/BRS-KB
Project-URL: Documentation, https://github.com/EPTLLC/BRS-KB#readme
Project-URL: Repository, https://github.com/EPTLLC/BRS-KB.git
Project-URL: Issues, https://github.com/EPTLLC/BRS-KB/issues
Project-URL: Changelog, https://github.com/EPTLLC/BRS-KB/blob/main/CHANGELOG.md
Project-URL: Discussions, https://github.com/EPTLLC/BRS-KB/discussions
Project-URL: API, https://brs-kb.easypro.tech
Author-email: Brabus <dev@easypro.tech>
Maintainer-email: EasyProTech LLC <contact@easypro.tech>
License-Expression: MIT
License-File: LICENSE
Keywords: appsec,bug-bounty,cvss,cwe,knowledge-base,owasp,payload,penetration-testing,red-team,security,security-research,vulnerability,waf-bypass,web-security,xss
Classifier: Development Status :: 5 - Production/Stable
Classifier: Environment :: Console
Classifier: Framework :: Pytest
Classifier: Intended Audience :: Developers
Classifier: Intended Audience :: Information Technology
Classifier: Intended Audience :: Science/Research
Classifier: License :: OSI Approved :: MIT License
Classifier: Operating System :: OS Independent
Classifier: Programming Language :: Python :: 3
Classifier: Programming Language :: Python :: 3.10
Classifier: Programming Language :: Python :: 3.11
Classifier: Programming Language :: Python :: 3.12
Classifier: Programming Language :: Python :: 3.13
Classifier: Programming Language :: Python :: Implementation :: CPython
Classifier: Topic :: Internet :: WWW/HTTP
Classifier: Topic :: Security
Classifier: Topic :: Software Development :: Libraries :: Python Modules
Classifier: Typing :: Typed
Requires-Python: >=3.10
Provides-Extra: all
Requires-Dist: black>=23.0; extra == 'all'
Requires-Dist: mypy>=1.0; extra == 'all'
Requires-Dist: pre-commit>=2.20; extra == 'all'
Requires-Dist: pytest-cov>=4.0; extra == 'all'
Requires-Dist: pytest-xdist>=3.0; extra == 'all'
Requires-Dist: pytest>=7.0; extra == 'all'
Requires-Dist: ruff>=0.1; extra == 'all'
Requires-Dist: starlette>=0.36; extra == 'all'
Requires-Dist: uvicorn>=0.27; extra == 'all'
Provides-Extra: dev
Requires-Dist: black>=23.0; extra == 'dev'
Requires-Dist: mypy>=1.0; extra == 'dev'
Requires-Dist: pre-commit>=2.20; extra == 'dev'
Requires-Dist: pytest-cov>=4.0; extra == 'dev'
Requires-Dist: pytest-xdist>=3.0; extra == 'dev'
Requires-Dist: pytest>=7.0; extra == 'dev'
Requires-Dist: ruff>=0.1; extra == 'dev'
Provides-Extra: server
Requires-Dist: starlette>=0.36; extra == 'server'
Requires-Dist: uvicorn>=0.27; extra == 'server'
